originlab/__init__.py
originlab/graph.py
originlab/matrix.py
originlab/project.py
originlab/worksheet.py
originlab-0.0.3.data/data/LICENSE.txt
originlab-0.0.3.dist-info/LICENSE.txt
originlab-0.0.3.dist-info/METADATA
originlab-0.0.3.dist-info/WHEEL
originlab-0.0.3.dist-info/top_level.txt
originlab-0.0.3.dist-info/RECORD
