Metadata-Version: 2.1
Name: originlab
Version: 0.0.3
Summary: Originlab Utilities
Home-page: https://www.originlab.com
Author: OriginLab
Author-email: folger@originlab.com.cn
License: BSD
Keywords: Origin,Originlab
Platform: Windows
Classifier: Programming Language :: Python :: 3
Classifier: License :: OSI Approved :: BSD License
Requires-Python: >=3.8
